[
  {
    "split":"train",
    "mse":0.0827930644,
    "rmse":0.2877378397,
    "r2":0.8423682451,
    "mae":0.2071627825,
    "nse":0.8423682451,
    "media_residuo":0.0030837171,
    "varianza_residuo":0.08278355,
    "errore_massimo":3.157271862
  },
  {
    "split":"test",
    "mse":0.0920228437,
    "rmse":0.3033526721,
    "r2":0.8317341805,
    "mae":0.2199285477,
    "nse":0.8317341805,
    "media_residuo":0.0323785432,
    "varianza_residuo":0.090974465,
    "errore_massimo":2.5126645565
  }
]